odoo/addons/stock_pull_list/README.rst
odoo/addons/stock_pull_list/__init__.py
odoo/addons/stock_pull_list/__manifest__.py
odoo/addons/stock_pull_list/data/data.xml
odoo/addons/stock_pull_list/data/stock_pull_list_sequence_data.xml
odoo/addons/stock_pull_list/i18n/it.po
odoo/addons/stock_pull_list/i18n/stock_pull_list.pot
odoo/addons/stock_pull_list/models/__init__.py
odoo/addons/stock_pull_list/models/stock_picking.py
odoo/addons/stock_pull_list/readme/CONTRIBUTORS.rst
odoo/addons/stock_pull_list/readme/DESCRIPTION.rst
odoo/addons/stock_pull_list/readme/ROADMAP.rst
odoo/addons/stock_pull_list/readme/USAGE.rst
odoo/addons/stock_pull_list/security/ir.model.access.csv
odoo/addons/stock_pull_list/static/description/icon.png
odoo/addons/stock_pull_list/static/description/index.html
odoo/addons/stock_pull_list/tests/__init__.py
odoo/addons/stock_pull_list/tests/common.py
odoo/addons/stock_pull_list/tests/test_stock_pull_list.py
odoo/addons/stock_pull_list/views/stock_picking_views.xml
odoo/addons/stock_pull_list/wizards/__init__.py
odoo/addons/stock_pull_list/wizards/stock_pull_list_wizard.py
odoo/addons/stock_pull_list/wizards/stock_pull_list_wizard.xml
odoo14_addon_stock_pull_list-14.0.1.2.1.dist-info/METADATA
odoo14_addon_stock_pull_list-14.0.1.2.1.dist-info/WHEEL
odoo14_addon_stock_pull_list-14.0.1.2.1.dist-info/top_level.txt
odoo14_addon_stock_pull_list-14.0.1.2.1.dist-info/RECORD
