Metadata-Version: 2.1
Name: odoo14-addon-stock-pull-list
Version: 14.0.1.2.1
Summary: The pull list checks the stock situation and calculates needed quantities.
Home-page: https://github.com/OCA/stock-logistics-warehouse
Author: ForgeFlow, Odoo Community Association (OCA)
Author-email: support@odoo-community.org
License: AGPL-3
Platform: UNKNOWN
Classifier: Programming Language :: Python
Classifier: Framework :: Odoo
Classifier: Framework :: Odoo :: 14.0
Classifier: License :: OSI Approved :: GNU Affero General Public License v3
Classifier: Development Status :: 3 - Alpha
Requires-Python: >=3.6
Requires-Dist: odoo14-addon-stock-free-quantity
Requires-Dist: odoo <14.1dev,>=14.0a
